[
  {
    "name": "Route 22",
    "children": [
      {
        "name": "Route 22 Rival",
        "sections": [
          {
            "ref": "Routes/Route 22/Early Rival Reward",
            "name": "Early Reward"
          },
          {
            "ref": "Routes/Route 22/Late Rival Reward",
            "name": "Late Reward"
          }
        ],
        "map_locations": [
          {
            "map": "route_22",
            "x": 408,
            "y": 88
          }
        ]
      },
      {
        "name": "Route 22 Gate (South)",
        "sections": [
          {
            "name": "Route 22 Gate (South)"
          }
        ],
        "map_locations": [
          {
            "map": "route_22",
            "x": 136,
            "y": 88
          }
        ]
      }
    ]
  },
  {
    "name": "Route 22 Gate",
    "children": [
      {
        "name": "Route 22 Gate Exit (North)",
        "sections": [
          {
            "name": "Route 22 Gate Exit (North)"
          }
        ],
        "map_locations": [
          {
            "map": "route_22_gate",
            "x": 120,
            "y": 24
          }
        ]
      },
      {
        "name": "Route 22 Gate Exit (South)",
        "sections": [
          {
            "name": "Route 22 Gate Exit (South)"
          }
        ],
        "map_locations": [
          {
            "map": "route_22_gate",
            "x": 120,
            "y": 168
          }
        ]
      }
    ]
  }
]