[
  {
    "name": "Fuchsia City",
    "children": [
      {
        "name": "Visit",
        "sections": [
          {
            "ref": "Cities/Fuchsia City/Unlock Fly Destination"
          }
        ],
        "map_locations": [
          {
            "map": "fuchsia_city",
            "x": 12,
            "y": 12
          }
        ]
      },
      {
        "name": "Gym Sign",
        "sections": [
          {
            "ref": "Cities/Fuchsia City/Gym Sign Info",
            "name": "Info"
          }
        ],
        "map_locations": [
          {
            "map": "fuchsia_city",
            "x": 88,
            "y": 520
          }
        ]
      },
      {
        "name": "Fishing Guru's House",
        "sections": [
          {
            "ref": "Cities/Fuchsia City/Fishing Guru Gift"
          }
        ],
        "map_locations": [
          {
            "map": "fuchsia_city",
            "x": 616,
            "y": 504
          }
        ]
      },
      {
        "name": "Hidden Item Behind Fishing Guru's House",
        "sections": [
          {
            "ref": "Cities/Fuchsia City/Hidden Item Behind Fishing Guru's House",
            "name": "Hidden Item"
          }
        ],
        "map_locations": [
          {
            "map": "fuchsia_city",
            "x": 536,
            "y": 424
          }
        ]
      },
      {
        "name": "Safari Zone Warden's House",
        "sections": [
          {
            "ref": "Cities/Fuchsia City/Safari Zone Warden Gift (Return Teeth)",
            "name": "Safari Zone Warden Gift (Return Teeth)"
          },
          {
            "ref": "Cities/Fuchsia City/Safari Zone Warden's House Item",
            "name": "Item"
          },
          {
            "ref": "Cities/Fuchsia City/Bookshelf Info",
            "name": "Bookshelf Info"
          }
        ],
        "map_locations": [
          {
            "map": "fuchsia_city",
            "x": 536,
            "y": 504
          }
        ]
      },
      {
        "name": "Koga's Daughter",
        "sections": [
          {
            "ref": "Cities/Fuchsia City/Koga's Daughter Info",
            "name": "Info"
          }
        ],
        "map_locations": [
          {
            "map": "fuchsia_city",
            "x": 648,
            "y": 104
          }
        ]
      },
      {
        "name": "Safari Zone Office",
        "sections": [
          {
            "ref": "Cities/Fuchsia City/Safari Zone Worker Gift"
          }
        ],
        "map_locations": [
          {
            "map": "fuchsia_city",
            "x": 456,
            "y": 264
          }
        ]
      },
      {
        "name": "Bill's Grandpa's House",
        "sections": [
          {
            "ref": "Cities/Fuchsia City/Bill's Grandpa Info"
          }
        ],
        "map_locations": [
          {
            "map": "fuchsia_city",
            "x": 232,
            "y": 504
          }
        ]
      },
      {
        "name": "Fuchsia Gym",
        "sections": [
          {
            "ref": "Cities/Fuchsia City/Juggler Nate Reward",
            "name": "Juggler Nate Reward"
          },
          {
            "ref": "Cities/Fuchsia City/Juggler Kayden Reward",
            "name": "Juggler Kayden Reward"
          },
          {
            "ref": "Cities/Fuchsia City/Juggler Kirk Reward",
            "name": "Juggler Kirk Reward"
          },
          {
            "ref": "Cities/Fuchsia City/Juggler Kirk Info",
            "name": "Juggler Kirk Info"
          },
          {
            "ref": "Cities/Fuchsia City/Tamer Edgar Reward",
            "name": "Tamer Edgar Reward"
          },
          {
            "ref": "Cities/Fuchsia City/Tamer Phil Reward",
            "name": "Tamer Phil Reward"
          },
          {
            "ref": "Cities/Fuchsia City/Juggler Shawn Reward",
            "name": "Juggler Shawn Reward"
          },
          {
            "ref": "Cities/Fuchsia City/Defeat Koga (Event)",
            "name": "Defeat Koga (Event)"
          },
          {
            "ref": "Cities/Fuchsia City/Leader Koga Reward",
            "name": "Leader Koga Reward"
          },
          {
            "ref": "Cities/Fuchsia City/Koga Info",
            "name": "Koga Info"
          },
          {
            "ref": "Cities/Fuchsia City/Fuchsia Gym Prize",
            "name": "Fuchsia Gym Prize"
          },
          {
            "ref": "Cities/Fuchsia City/Koga TM",
            "name": "Koga TM"
          }
        ],
        "map_locations": [
          {
            "map": "fuchsia_city",
            "x": 152,
            "y": 520
          }
        ]
      }
    ]
  },
  {
    "name": "Safari Zone Office",
    "children": [
      {
        "name": "Worker",
        "sections": [
          {
            "ref": "Cities/Fuchsia City/Safari Zone Worker Gift",
            "name": "Gift"
          }
        ],
        "map_locations": [
          {
            "map": "safari_zone_office",
            "x": 104,
            "y": 72
          }
        ]
      }
    ]
  },
  {
    "name": "Fuchsia Gym",
    "children": [
      {
        "name": "Juggler Nate",
        "sections": [
          {
            "ref": "Cities/Fuchsia City/Juggler Nate Reward",
            "name": "Reward"
          }
        ],
        "map_locations": [
          {
            "map": "fuchsia_gym",
            "x": 40,
            "y": 264
          }
        ]
      },
      {
        "name": "Juggler Kayden",
        "sections": [
          {
            "ref": "Cities/Fuchsia City/Juggler Kayden Reward",
            "name": "Reward"
          }
        ],
        "map_locations": [
          {
            "map": "fuchsia_gym",
            "x": 200,
            "y": 264
          }
        ]
      },
      {
        "name": "Juggler Kirk",
        "sections": [
          {
            "ref": "Cities/Fuchsia City/Juggler Kirk Reward",
            "name": "Reward"
          },
          {
            "ref": "Cities/Fuchsia City/Juggler Kirk Info",
            "name": "Info"
          }
        ],
        "map_locations": [
          {
            "map": "fuchsia_gym",
            "x": 184,
            "y": 184
          }
        ]
      },
      {
        "name": "Tamer Edgar",
        "sections": [
          {
            "ref": "Cities/Fuchsia City/Tamer Edgar Reward",
            "name": "Reward"
          }
        ],
        "map_locations": [
          {
            "map": "fuchsia_gym",
            "x": 216,
            "y": 72
          }
        ]
      },
      {
        "name": "Tamer Phil",
        "sections": [
          {
            "ref": "Cities/Fuchsia City/Tamer Phil Reward",
            "name": "Reward"
          }
        ],
        "map_locations": [
          {
            "map": "fuchsia_gym",
            "x": 72,
            "y": 104
          }
        ]
      },
      {
        "name": "Juggler Shawn",
        "sections": [
          {
            "ref": "Cities/Fuchsia City/Juggler Shawn Reward",
            "name": "Reward"
          }
        ],
        "map_locations": [
          {
            "map": "fuchsia_gym",
            "x": 40,
            "y": 152
          }
        ]
      },
      {
        "name": "Koga",
        "sections": [
          {
            "ref": "Cities/Fuchsia City/Defeat Koga (Event)",
            "name": "Defeat Koga (Event)"
          },
          {
            "ref": "Cities/Fuchsia City/Leader Koga Reward",
            "name": "Reward"
          },
          {
            "ref": "Cities/Fuchsia City/Koga Info",
            "name": "Info"
          },
          {
            "ref": "Cities/Fuchsia City/Fuchsia Gym Prize",
            "name": "Gym Prize"
          },
          {
            "ref": "Cities/Fuchsia City/Koga TM",
            "name": "TM"
          }
        ],
        "map_locations": [
          {
            "map": "fuchsia_gym",
            "x": 120,
            "y": 216
          }
        ]
      }
    ]
  },
  {
    "name": "Bill's Grandpa's House",
    "children": [
      {
        "name": "Bill's Grandpa",
        "sections": [
          {
            "ref": "Cities/Fuchsia City/Bill's Grandpa Info",
            "name": "Info"
          }
        ],
        "map_locations": [
          {
            "map": "bills_grandpas_house",
            "x": 120,
            "y": 72
          }
        ]
      }
    ]
  },
  {
    "name": "Safari Zone Warden's House",
    "children": [
      {
        "name": "Safari Zone Warden",
        "sections": [
          {
            "ref": "Cities/Fuchsia City/Safari Zone Warden Gift (Return Teeth)",
            "name": "Gift (Return Teeth)"
          }
        ],
        "map_locations": [
          {
            "map": "safari_zone_wardens_house",
            "x": 56,
            "y": 88
          }
        ]
      },
      {
        "name": "Item",
        "sections": [
          {
            "ref": "Cities/Fuchsia City/Safari Zone Warden's House Item",
            "name": "Item"
          }
        ],
        "map_locations": [
          {
            "map": "safari_zone_wardens_house",
            "x": 184,
            "y": 88
          }
        ]
      },
      {
        "name": "Bookshelf",
        "sections": [
          {
            "ref": "Cities/Fuchsia City/Bookshelf Info",
            "name": "Info"
          }
        ],
        "map_locations": [
          {
            "map": "safari_zone_wardens_house",
            "x": 72,
            "y": 32
          }
        ]
      }
    ]
  },
  {
    "name": "Fuchsia Fishing House",
    "children": [
      {
        "name": "Fishing Guru",
        "sections": [
          {
            "ref": "Cities/Fuchsia City/Fishing Guru Gift",
            "name": "Gift"
          }
        ],
        "map_locations": [
          {
            "map": "fuchsia_fishing_house",
            "x": 104,
            "y": 88
          }
        ]
      }
    ]
  }
]