[
  {
    "name": "Cities",
    "children": [
      {
        "name": "Pallet Town",
        "sections": [
          {
            "name": "Unlock Fly Destination"
          },
          {
            "name": "PC Item"
          },
          {
            "name": "Pallet Town - Oak's Lab Sign Info"
          },
          {
            "name": "Professor Oak's Lab - Rival Reward"
          },
          {
            "name": "Professor Oak's Lab - Oak Gift 1 (Deliver Parcel)"
          },
          {
            "name": "Professor Oak's Lab - Oak Gift 2 (Deliver Parcel)"
          },
          {
            "name": "Professor Oak's Lab - Oak Info"
          },
          {
            "name": "Professor Oak's Lab - Oak Gift (Post Route 22 Rival)"
          },
          {
            "name": "Professor Oak's Lab - Oak's Aide F Info"
          },
          {
            "name": "Professor Oak's Lab - Oak's Aide M Info (Right)"
          },
          {
            "name": "Professor Oak's Lab - Oak's Aide M Info (Left)"
          },
          {
            "name": "Rival's House - Daisy Gift"
          }
        ],
        "map_locations": [
          {
            "map": "kanto_sevii",
            "x": 44,
            "y": 108
          },
          {
            "map": "kanto",
            "x": 44,
            "y": 108
          }
        ]
      },
      {
        "name": "Viridian City",
        "sections": [
          {
            "name": "Unlock Fly Destination"
          },
          {
            "name": "PC Item"
          },
          {
            "name": "Viridian Poke Mart - Delivery for Oak"
          },
          {
            "name": "Shop Item 1"
          },
          {
            "name": "Shop Item 2"
          },
          {
            "name": "Shop Item 3"
          },
          {
            "name": "Shop Item 4"
          },
          {
            "name": "Viridian School - Bookshelf Info 1"
          },
          {
            "name": "Viridian School - Bookshelf Info 2"
          },
          {
            "name": "Viridian City - Item Near Cuttable Tree"
          },
          {
            "name": "Viridian City - Tutorial Man Gift"
          },
          {
            "name": "Viridian City - Old Man Gift"
          },
          {
            "name": "Viridian Gym - Gym Guy Info"
          },
          {
            "name": "Viridian Gym - Tamer Cole Reward"
          },
          {
            "name": "Viridian Gym - Black Belt Kiyo Reward"
          },
          {
            "name": "Viridian Gym - Cooltrainer Samuel Reward"
          },
          {
            "name": "Viridian Gym - Cooltrainer Yuji Reward"
          },
          {
            "name": "Viridian Gym - Black Belt Atsushi Reward"
          },
          {
            "name": "Viridian Gym - Tamer Jason Reward"
          },
          {
            "name": "Viridian Gym - Cooltrainer Warren Reward"
          },
          {
            "name": "Viridian Gym - Black Belt Takashi Reward"
          },
          {
            "name": "Viridian Gym - Leader Giovanni Reward"
          },
          {
            "name": "Viridian Gym - Giovanni Info"
          },
          {
            "name": "Viridian Gym - Prize"
          },
          {
            "name": "Viridian Gym - Giovanni TM"
          },
          {
            "name": "Viridian Gym - Hidden Item Under Giovanni"
          }
        ],
        "map_locations": [
          {
            "map": "kanto_sevii",
            "x": 44,
            "y": 84
          },
          {
            "map": "kanto",
            "x": 44,
            "y": 84
          }
        ]
      },
      {
        "name": "Pewter City",
        "sections": [
          {
            "name": "Unlock Fly Destination"
          },
          {
            "name": "PC Item"
          },
          {
            "name": "Pewter City - Fat Man Info"
          },
          {
            "name": "Shop Item 1"
          },
          {
            "name": "Shop Item 2"
          },
          {
            "name": "Shop Item 3"
          },
          {
            "name": "Shop Item 4"
          },
          {
            "name": "Shop Item 5"
          },
          {
            "name": "Shop Item 6"
          },
          {
            "name": "Shop Item 7"
          },
          {
            "name": "Shop Item 8"
          },
          {
            "name": "Pewter City - Northwest Hidden Item"
          },
          {
            "name": "Pewter City - Gym Sign Info"
          },
          {
            "name": "Pewter Museum 2F - Item"
          },
          {
            "name": "Pewter Museum 1F - Scientist Gift"
          },
          {
            "name": "Pewter Museum 1F - Bookshelf Info"
          },
          {
            "name": "Pewter City - Gift from Mom"
          },
          {
            "name": "Pewter Gym - Camper Liam Reward"
          },
          {
            "name": "Pewter Gym - Leader Brock Reward"
          },
          {
            "name": "Pewter Gym - Brock Info"
          },
          {
            "name": "Pewter Gym - Prize"
          },
          {
            "name": "Pewter Gym - Brock TM"
          }
        ],
        "map_locations": [
          {
            "map": "kanto_sevii",
            "x": 44,
            "y": 52
          },
          {
            "map": "kanto",
            "x": 44,
            "y": 52
          }
        ]
      },
      {
        "name": "Cerulean City",
        "sections": [
          {
            "name": "Unlock Fly Destination"
          },
          {
            "name": "PC Item"
          },
          {
            "name": "Cerulean City - Hidden Item Behind Badge Guy's House"
          },
          {
            "name": "Berry Powder Man's House - Berry Powder Man Gift"
          },
          {
            "name": "Cerulean City - Rival Info"
          },
          {
            "name": "Cerulean City - Rival Reward"
          },
          {
            "name": "Cerulean City - Rival Gift"
          },
          {
            "name": "Cerulean Pokemon Center 1F - Youngster Info"
          },
          {
            "name": "Cerulean Pokemon Center 1F - Bookshelf Info"
          },
          {
            "name": "Cerulean City - Gym Sign Info"
          },
          {
            "name": "Bike Shop - Bicycle Purchase"
          },
          {
            "name": "Shop Item 1"
          },
          {
            "name": "Shop Item 2"
          },
          {
            "name": "Shop Item 3"
          },
          {
            "name": "Shop Item 4"
          },
          {
            "name": "Shop Item 5"
          },
          {
            "name": "Shop Item 6"
          },
          {
            "name": "Shop Item 7"
          },
          {
            "name": "Shop Item 8"
          },
          {
            "name": "Shop Item 9"
          },
          {
            "name": "Cerulean City - Team Rocket Grunt Reward"
          },
          {
            "name": "Cerulean City - Recover Stolen TM"
          },
          {
            "name": "Cerulean Gym - Hidden Item in Water"
          },
          {
            "name": "Cerulean Gym - Swimmer Luis Reward"
          },
          {
            "name": "Cerulean Gym - Swimmer Luis Info"
          },
          {
            "name": "Cerulean Gym - Picnicker Diana Reward"
          },
          {
            "name": "Cerulean Gym - Leader Misty Reward"
          },
          {
            "name": "Cerulean Gym - Misty Info"
          },
          {
            "name": "Cerulean Gym - Prize"
          },
          {
            "name": "Cerulean Gym - Misty TM"
          }
        ],
        "map_locations": [
          {
            "map": "kanto_sevii",
            "x": 124,
            "y": 44
          },
          {
            "map": "kanto",
            "x": 124,
            "y": 44
          }
        ]
      },
      {
        "name": "Vermilion City",
        "sections": [
          {
            "name": "Unlock Fly Destination"
          },
          {
            "name": "PC Item"
          },
          {
            "name": "Vermilion City - Hidden Item Near Pokemon Center"
          },
          {
            "name": "Vermilion Pokemon Center 1F - Vs. Seeker Woman Gift"
          },
          {
            "name": "Vermilion Pokemon Center 1F - Bookshelf Info"
          },
          {
            "name": "Vermilion Fishing House - Fishing Guru Gift"
          },
          {
            "name": "Shop Item 1"
          },
          {
            "name": "Shop Item 2"
          },
          {
            "name": "Shop Item 3"
          },
          {
            "name": "Shop Item 4"
          },
          {
            "name": "Shop Item 5"
          },
          {
            "name": "Shop Item 6"
          },
          {
            "name": "Shop Item 7"
          },
          {
            "name": "Pokemon Fan Club - Chairman Gift"
          },
          {
            "name": "Pokemon Fan Club - Worker Info"
          },
          {
            "name": "Vermilion City - Gym Sign Info"
          },
          {
            "name": "Vermilion Gym - Sailor Dwayne Reward"
          },
          {
            "name": "Vermilion Gym - Sailor Dwayne Info"
          },
          {
            "name": "Vermilion Gym - Engineer Baily Reward"
          },
          {
            "name": "Vermilion Gym - Gentleman Tucker Reward"
          },
          {
            "name": "Vermilion Gym - Gentleman Tucker Info 1"
          },
          {
            "name": "Vermilion Gym - Gentleman Tucker Info 2"
          },
          {
            "name": "Vermilion Gym - Lt. Surge Info"
          },
          {
            "name": "Vermilion Gym - Leader Lt. Surge Reward"
          },
          {
            "name": "Vermilion Gym - Prize"
          },
          {
            "name": "Vermilion Gym - Lt. Surge TM"
          }
        ],
        "map_locations": [
          {
            "map": "kanto_sevii",
            "x": 124,
            "y": 92
          },
          {
            "map": "kanto",
            "x": 124,
            "y": 92
          }
        ]
      },
      {
        "name": "Lavender Town",
        "sections": [
          {
            "name": "Unlock Fly Destination"
          },
          {
            "name": "PC Item"
          },
          {
            "name": "Lavender Pokemon Center 1F - Balding Man Info"
          },
          {
            "name": "Volunteer Pokemon House - Little Girl Info"
          },
          {
            "name": "Volunteer Pokemon House - Journal Info"
          },
          {
            "name": "Volunteer Pokemon House - Mr. Fuji Gift"
          },
          {
            "name": "Shop Item 1"
          },
          {
            "name": "Shop Item 2"
          },
          {
            "name": "Shop Item 3"
          },
          {
            "name": "Shop Item 4"
          },
          {
            "name": "Shop Item 5"
          },
          {
            "name": "Shop Item 6"
          },
          {
            "name": "Shop Item 7"
          },
          {
            "name": "Shop Item 8"
          },
          {
            "name": "Shop Item 9"
          }
        ],
        "map_locations": [
          {
            "map": "kanto_sevii",
            "x": 156,
            "y": 68
          },
          {
            "map": "kanto",
            "x": 156,
            "y": 68
          }
        ]
      },
      {
        "name": "Celadon City",
        "sections": [
          {
            "name": "Unlock Fly Destination"
          },
          {
            "name": "PC Item"
          },
          {
            "name": "Celadon City - Northwest Item"
          },
          {
            "name": "Celadon Condominiums 1F - Tea Woman Gift"
          },
          {
            "name": "Celadon Condominiums 1F - Tea Woman Info"
          },
          {
            "name": "Celadon Condominiums 1F - Brock Gift"
          },
          {
            "name": "Celadon Condominiums 1F - Misty Gift"
          },
          {
            "name": "Celadon Condominiums 1F - Erika Gift"
          },
          {
            "name": "Celadon Condominiums 2F - Bookshelf Info"
          },
          {
            "name": "TM Shop Item 1"
          },
          {
            "name": "TM Shop Item 2"
          },
          {
            "name": "TM Shop Item 3"
          },
          {
            "name": "TM Shop Item 4"
          },
          {
            "name": "TM Shop Item 5"
          },
          {
            "name": "TM Shop Item 6"
          },
          {
            "name": "Shop Item 1"
          },
          {
            "name": "Shop Item 2"
          },
          {
            "name": "Shop Item 3"
          },
          {
            "name": "Shop Item 4"
          },
          {
            "name": "Shop Item 5"
          },
          {
            "name": "Shop Item 6"
          },
          {
            "name": "Shop Item 7"
          },
          {
            "name": "Shop Item 8"
          },
          {
            "name": "Shop Item 9"
          },
          {
            "name": "Celadon Department Store 2F - Woman Info"
          },
          {
            "name": "Evo Shop Item 1"
          },
          {
            "name": "Evo Shop Item 2"
          },
          {
            "name": "Evo Shop Item 3"
          },
          {
            "name": "Evo Shop Item 4"
          },
          {
            "name": "Evo Shop Item 5"
          },
          {
            "name": "Evo Shop Item 6"
          },
          {
            "name": "Vitamin Shop Item 1"
          },
          {
            "name": "Vitamin Shop Item 2"
          },
          {
            "name": "Vitamin Shop Item 3"
          },
          {
            "name": "Vitamin Shop Item 4"
          },
          {
            "name": "Vitamin Shop Item 5"
          },
          {
            "name": "Vitamin Shop Item 6"
          },
          {
            "name": "Battle Shop Item 1"
          },
          {
            "name": "Battle Shop Item 2"
          },
          {
            "name": "Battle Shop Item 3"
          },
          {
            "name": "Battle Shop Item 4"
          },
          {
            "name": "Battle Shop Item 5"
          },
          {
            "name": "Battle Shop Item 6"
          },
          {
            "name": "Battle Shop Item 7"
          },
          {
            "name": "Vending Machine Item 1"
          },
          {
            "name": "Vending Machine Item 2"
          },
          {
            "name": "Vending Machine Item 3"
          },
          {
            "name": "Celadon Department Store Roof - Thirsty Girl Gift (Give Fresh Water)"
          },
          {
            "name": "Celadon Department Store Roof - Thirsty Girl Gift (Give Soda Pop)"
          },
          {
            "name": "Celadon Department Store Roof - Thirsty Girl Gift (Give Lemonade)"
          },
          {
            "name": "Celadon Restaurant - Coin Case Man Gift"
          },
          {
            "name": "Celadon Rocket House - Item"
          },
          {
            "name": "Celadon Hotel - Item"
          },
          {
            "name": "Celadon City - Hidden Item Near Cuttable Tree"
          },
          {
            "name": "Celadon Game Corner - Fisherman Gift"
          },
          {
            "name": "Celadon Game Corner - Scientist Gift"
          },
          {
            "name": "Celadon Game Corner - Gentleman Gift"
          },
          {
            "name": "Celadon Game Corner - Southwest Hidden Item"
          },
          {
            "name": "Celadon Game Corner - South Hidden Item (Left)"
          },
          {
            "name": "Celadon Game Corner - South Hidden Item (Right)"
          },
          {
            "name": "Celadon Game Corner - Southeast Hidden Item"
          },
          {
            "name": "Celadon Game Corner - West Hidden Item"
          },
          {
            "name": "Celadon Game Corner - Center Hidden Item"
          },
          {
            "name": "Celadon Game Corner - East Hidden Item (Left)"
          },
          {
            "name": "Celadon Game Corner - East Hidden Item (Right)"
          },
          {
            "name": "Celadon Game Corner - Northwest Hidden Item"
          },
          {
            "name": "Celadon Game Corner - North Hidden Item (Left)"
          },
          {
            "name": "Celadon Game Corner - North Hidden Item (Right)"
          },
          {
            "name": "Celadon Game Corner - Northeast Hidden Item"
          },
          {
            "name": "Celadon Game Corner - Team Rocket Grunt Reward"
          },
          {
            "name": "Prize Item 1"
          },
          {
            "name": "Prize Item 2"
          },
          {
            "name": "Prize Item 3"
          },
          {
            "name": "Prize Item 4"
          },
          {
            "name": "Prize Item 5"
          },
          {
            "name": "Prize TM 1"
          },
          {
            "name": "Prize TM 2"
          },
          {
            "name": "Prize TM 3"
          },
          {
            "name": "Prize TM 4"
          },
          {
            "name": "Prize TM 5"
          },
          {
            "name": "Celadon City - Gym Sign Info"
          },
          {
            "name": "Celadon Gym - Lass Kay Reward"
          },
          {
            "name": "Celadon Gym - Beauty Bridget Reward"
          },
          {
            "name": "Celadon Gym - Beauty Tamia Reward"
          },
          {
            "name": "Celadon Gym - Beauty Tamia Info"
          },
          {
            "name": "Celadon Gym - Picnicker Tina Reward"
          },
          {
            "name": "Celadon Gym - Cooltrainer Mary Reward"
          },
          {
            "name": "Celadon Gym - Beauty Lori Reward"
          },
          {
            "name": "Celadon Gym - Lass Lisa Reward"
          },
          {
            "name": "Celadon Gym - Lass Lisa Info"
          },
          {
            "name": "Celadon Gym - Leader Erika Reward"
          },
          {
            "name": "Celadon Gym - Erika Info 1"
          },
          {
            "name": "Celadon Gym - Prize"
          },
          {
            "name": "Celadon Gym - Erika TM"
          },
          {
            "name": "Celadon Gym - Erika Info 2"
          }
        ],
        "map_locations": [
          {
            "map": "kanto_sevii",
            "x": 100,
            "y": 68
          },
          {
            "map": "kanto",
            "x": 100,
            "y": 68
          }
        ]
      },
      {
        "name": "Fuchsia City",
        "sections": [
          {
            "name": "Unlock Fly Destination"
          },
          {
            "name": "PC Item"
          },
          {
            "name": "Fuchsia Fishing House - Fishing Guru Gift"
          },
          {
            "name": "Fuchsia City - Hidden Item Behind Fishing Guru's House"
          },
          {
            "name": "Safari Zone Warden's House - Warden Gift (Return Teeth)"
          },
          {
            "name": "Safari Zone Warden's House - Item"
          },
          {
            "name": "Safari Zone Warden's House - Bookshelf Info"
          },
          {
            "name": "Safari Zone Office - Safari Zone Worker Gift"
          },
          {
            "name": "Shop Item 1"
          },
          {
            "name": "Shop Item 2"
          },
          {
            "name": "Shop Item 3"
          },
          {
            "name": "Shop Item 4"
          },
          {
            "name": "Shop Item 5"
          },
          {
            "name": "Shop Item 6"
          },
          {
            "name": "Fuchsia City - Koga's Daughter Info"
          },
          {
            "name": "Bill's Grandpa's House - Bill's Grandpa Info"
          },
          {
            "name": "Fuchsia City - Gym Sign Info"
          },
          {
            "name": "Fuchsia Gym - Juggler Nate Reward"
          },
          {
            "name": "Fuchsia Gym - Juggler Kayden Reward"
          },
          {
            "name": "Fuchsia Gym - Juggler Kirk Reward"
          },
          {
            "name": "Fuchsia Gym - Juggler Kirk Info"
          },
          {
            "name": "Fuchsia Gym - Tamer Edgar Reward"
          },
          {
            "name": "Fuchsia Gym - Tamer Phil Reward"
          },
          {
            "name": "Fuchsia Gym - Juggler Shawn Reward"
          },
          {
            "name": "Fuchsia Gym - Leader Koga Reward"
          },
          {
            "name": "Fuchsia Gym - Koga Info"
          },
          {
            "name": "Fuchsia Gym - Prize"
          },
          {
            "name": "Fuchsia Gym - Koga TM"
          }
        ],
        "map_locations": [
          {
            "map": "kanto_sevii",
            "x": 108,
            "y": 116
          },
          {
            "map": "kanto",
            "x": 108,
            "y": 116
          }
        ]
      },
      {
        "name": "Saffron City",
        "sections": [
          {
            "name": "Unlock Fly Destination"
          },
          {
            "name": "PC Item"
          },
          {
            "name": "Saffron Pokemon Center 1F - Bookshelf Info"
          },
          {
            "name": "Mr. Psychic's House - Mr. Psychic Gift"
          },
          {
            "name": "Saffron City - Battle Girl Info"
          },
          {
            "name": "Pokemon Trainer Fan Club - Bookshelf Info"
          },
          {
            "name": "Shop Item 1"
          },
          {
            "name": "Shop Item 2"
          },
          {
            "name": "Shop Item 3"
          },
          {
            "name": "Shop Item 4"
          },
          {
            "name": "Shop Item 5"
          },
          {
            "name": "Shop Item 6"
          },
          {
            "name": "Saffron City - Gym Sign Info"
          },
          {
            "name": "Saffron Dojo - Black Belt Hideki Reward"
          },
          {
            "name": "Saffron Dojo - Black Belt Hitoshi Reward"
          },
          {
            "name": "Saffron Dojo - Black Belt Mike Reward"
          },
          {
            "name": "Saffron Dojo - Black Belt Aaron Reward"
          },
          {
            "name": "Saffron Dojo - Black Belt Koichi Reward"
          },
          {
            "name": "Saffron Dojo - Item (Center)"
          },
          {
            "name": "Copycat's House 2F - Desk Hidden Item"
          },
          {
            "name": "Saffron Gym - Psychic Cameron Reward"
          },
          {
            "name": "Saffron Gym - Channeler Tasha Reward"
          },
          {
            "name": "Saffron Gym - Psychic Tyron Reward"
          },
          {
            "name": "Saffron Gym - Psychic Tyron Info"
          },
          {
            "name": "Saffron Gym - Channeler Stacy Reward"
          },
          {
            "name": "Saffron Gym - Psychic Johan Reward"
          },
          {
            "name": "Saffron Gym - Channeler Amanda Reward"
          },
          {
            "name": "Saffron Gym - Psychic Preston Reward"
          },
          {
            "name": "Saffron Gym - Leader Sabrina Reward"
          },
          {
            "name": "Saffron Gym - Sabrina Info 1"
          },
          {
            "name": "Saffron Gym - Sabrina Info 2"
          },
          {
            "name": "Saffron Gym - Prize"
          },
          {
            "name": "Saffron Gym - Sabrina TM"
          }
        ],
        "map_locations": [
          {
            "map": "kanto_sevii",
            "x": 124,
            "y": 68
          },
          {
            "map": "kanto",
            "x": 124,
            "y": 68
          }
        ]
      },
      {
        "name": "Cinnabar Island",
        "sections": [
          {
            "name": "Unlock Fly Destination"
          },
          {
            "name": "PC Item"
          },
          {
            "name": "Shop Item 1"
          },
          {
            "name": "Shop Item 2"
          },
          {
            "name": "Shop Item 3"
          },
          {
            "name": "Shop Item 4"
          },
          {
            "name": "Shop Item 5"
          },
          {
            "name": "Shop Item 6"
          },
          {
            "name": "Shop Item 7"
          },
          {
            "name": "Cinnabar Island - Gym Sign Info"
          },
          {
            "name": "Cinnabar Island - Woman Info"
          },
          {
            "name": "Cinnabar Pokemon Center 1F - Bookshelf Info"
          },
          {
            "name": "Pokemon Lab Research Room - Scientist Gift"
          },
          {
            "name": "Pokemon Lab Experiment Room - Fossil"
          },
          {
            "name": "Cinnabar Pokemon Center 1F - Bill Gift"
          },
          {
            "name": "Cinnabar Gym - Burglar Quinn Reward"
          },
          {
            "name": "Cinnabar Gym - Super Nerd Erik Reward"
          },
          {
            "name": "Cinnabar Gym - Super Nerd Avery Reward"
          },
          {
            "name": "Cinnabar Gym - Burglar Ramon Reward"
          },
          {
            "name": "Cinnabar Gym - Super Nerd Derek Reward"
          },
          {
            "name": "Cinnabar Gym - Super Nerd Derek Info"
          },
          {
            "name": "Cinnabar Gym - Burglar Dusty Reward"
          },
          {
            "name": "Cinnabar Gym - Super Nerd Zac Reward"
          },
          {
            "name": "Cinnabar Gym - Leader Blaine Reward"
          },
          {
            "name": "Cinnabar Gym - Blaine Info"
          },
          {
            "name": "Cinnabar Gym - Prize"
          },
          {
            "name": "Cinnabar Gym - Blaine TM"
          },
          {
            "name": "Cinnabar Gym - Photo Info 1"
          },
          {
            "name": "Cinnabar Gym - Photo Info 2"
          }
        ],
        "map_locations": [
          {
            "map": "kanto_sevii",
            "x": 44,
            "y": 132
          },
          {
            "map": "kanto",
            "x": 44,
            "y": 132
          }
        ]
      },
      {
        "name": "Indigo Plateau",
        "sections": [
          {
            "name": "Unlock Fly Destination"
          },
          {
            "name": "PC Item"
          },
          {
            "name": "Shop Item 1"
          },
          {
            "name": "Shop Item 2"
          },
          {
            "name": "Shop Item 3"
          },
          {
            "name": "Shop Item 4"
          },
          {
            "name": "Shop Item 5"
          },
          {
            "name": "Shop Item 6"
          },
          {
            "name": "Shop Item 7"
          },
          {
            "name": "Indigo Plateau Pokemon Center 1F - Cooltrainer Info"
          },
          {
            "name": "Indigo Plateau Pokemon Center 1F - Black Belt Info 1"
          },
          {
            "name": "Indigo Plateau Pokemon Center 1F - Black Belt Info 2"
          },
          {
            "name": "Indigo Plateau Pokemon Center 1F - Bookshelf Info"
          },
          {
            "name": "Lorelei's Room - Lorelei Info 1"
          },
          {
            "name": "Lorelei's Room - Lorelei Info 2"
          },
          {
            "name": "Lorelei's Room - Elite Four Lorelei Reward"
          },
          {
            "name": "Bruno's Room - Bruno Info 1"
          },
          {
            "name": "Bruno's Room - Bruno Info 2"
          },
          {
            "name": "Bruno's Room - Elite Four Bruno Reward"
          },
          {
            "name": "Agatha's Room - Agatha Info 1"
          },
          {
            "name": "Agatha's Room - Agatha Info 2"
          },
          {
            "name": "Agatha's Room - Agatha Info 3"
          },
          {
            "name": "Agatha's Room - Elite Four Agatha Reward"
          },
          {
            "name": "Lance's Room - Lance Info 1"
          },
          {
            "name": "Lance's Room - Lance Info 2"
          },
          {
            "name": "Lance's Room - Elite Four Lance Reward"
          },
          {
            "name": "Champion's Room - Champion Reward"
          },
          {
            "name": "Hall of Fame - Oak Gift 1"
          },
          {
            "name": "Hall of Fame - Oak Gift 2"
          },
          {
            "name": "Lorelei's Room - Elite Four Lorelei Rematch Reward"
          },
          {
            "name": "Bruno's Room - Elite Four Bruno Rematch Reward"
          },
          {
            "name": "Agatha's Room - Elite Four Agatha Rematch Reward"
          },
          {
            "name": "Lance's Room - Elite Four Lance Rematch Reward"
          },
          {
            "name": "Champion's Room - Champion Rematch Reward"
          }
        ],
        "map_locations": [
          {
            "map": "kanto_sevii",
            "x": 28,
            "y": 44
          },
          {
            "map": "kanto",
            "x": 28,
            "y": 44
          }
        ]
      }
    ]
  }
]