[
  {
    "name": "Five Island Town",
    "children": [
      {
        "name": "Five Island Visit",
        "sections": [
          {
            "ref": "Islands/Five Island Town/Unlock Fly Destination",
            "name": "Unlock Fly Destination"
          }
        ],
        "map_locations": [
          {
            "map": "five_island",
            "x": 12,
            "y": 12
          }
        ]
      }
    ]
  },
  {
    "name": "Five Island Pokémon Center 1F",
    "children": [
      {
        "name": "Five Island Pokémon Center PC",
        "sections": [
          {
            "ref": "Islands/Five Island Town/PC Item",
            "name": "Item"
          }
        ],
        "map_locations": [
          {
            "map": "five_island_pokemon_center_1f",
            "x": 184,
            "y": 24
          }
        ]
      },
      {
        "name": "Five Island Pokémon Center Bookshelf",
        "sections": [
          {
            "ref": "Islands/Five Island Town/Bookshelf Info",
            "name": "Info"
          }
        ],
        "map_locations": [
          {
            "map": "five_island_pokemon_center_1f",
            "x": 48,
            "y": 32
          }
        ]
      }
    ]
  }
]